vt100logging/__init__.py
vt100logging/vt100logging.py
vt100logging-1.1.0.dist-info/LICENSE
vt100logging-1.1.0.dist-info/METADATA
vt100logging-1.1.0.dist-info/WHEEL
vt100logging-1.1.0.dist-info/top_level.txt
vt100logging-1.1.0.dist-info/RECORD
