Metadata-Version: 2.1
Name: vt100logging
Version: 1.1.0
Summary: VT100 logging for Python
Author-email: Grzegorz Grzęda <grzegorz.grzeda@g2labs.pl>
Project-URL: Homepage, https://github.com/g2labs-grzegorz-grzeda/vt100logging
Project-URL: Issues, https://github.com/g2labs-grzegorz-grzeda/vt100logging/issues
Classifier: Programming Language :: Python :: 3
Classifier: License :: OSI Approved :: MIT License
Classifier: Operating System :: OS Independent
Requires-Python: >=3.8
License-File: LICENSE
